{"id":1732,"question":"Aspek kesatuan berdasarkan sumpah pemuda yaitu ...","tags":"","subject":"Tes Wawasan Kebangsaan","answers":[{"question_id":1732,"id":8645,"jawaban":"Aspek satu nusa, aspek satu bangsa dan aspek satu bahasa","nilai":1},{"question_id":1732,"id":8646,"jawaban":"Aspek satu nusa, aspek satu rakyat dan aspek satu bahasa","nilai":0},{"question_id":1732,"id":8647,"jawaban":"Aspek satu negara, aspek satu bangsa dan aspek satu bahasa","nilai":0},{"question_id":1732,"id":8648,"jawaban":"Aspek satu nusa, aspek satu bangsa dan aspek satu perjuangan","nilai":0},{"question_id":1732,"id":8649,"jawaban":"Aspek satu nusa, aspek satu negara dan aspek satu bahasa","nilai":0}]}