{"id":1819,"question":"\"Penulisan nama dan gelar yang benar adalah ...","tags":"","subject":"Tes Wawasan Kebangsaan","answers":[{"question_id":1819,"id":9080,"jawaban":"Sutinah Pertiwi, S. H.","nilai":0},{"question_id":1819,"id":9081,"jawaban":"Moh Indrawan Setyo Hadi M.Pd.","nilai":0},{"question_id":1819,"id":9082,"jawaban":"Hj Rusti Sariringsih.","nilai":0},{"question_id":1819,"id":9083,"jawaban":"Dr. Laila Sari Devi","nilai":1},{"question_id":1819,"id":9084,"jawaban":"Rusli Hadiningrat, S. S","nilai":0}]}