{"id":1878,"question":"9. Anda adalah seorang ASN di tempat anda mengabdi terdapat banyak rekan rekan kerja dari berbagai suku, karena banyak perbedaan terutama pada gaya bahasa menyebabkan terjadi konflik, hal tersebut membuat adanya 2 kubu di tempat kerja anda. Bagaimana tindakan anda","tags":"","subject":"Tes Karakteristik Pribadi","answers":[{"question_id":1878,"id":9375,"jawaban":". Memupuk kesadaran toleransi antara rekan \u2013 rekan sekerja","nilai":4},{"question_id":1878,"id":9376,"jawaban":"Melakukan mediasi terhadap kedua kubu yang terlibat konflik","nilai":5},{"question_id":1878,"id":9377,"jawaban":"Ikut membela salah satu kubu yang saya anggap lebih benar","nilai":1},{"question_id":1878,"id":9378,"jawaban":"Mencegah kedua kubu tersebut untuk bertikai","nilai":3},{"question_id":1878,"id":9379,"jawaban":". Mengamati dan menganalisa mengapa konflik tersebut bisa terjadi","nilai":2}]}