{"id":2,"question":"<p>Nilai <span class=\"math-tex\">\\(x\\)<\/span>&nbsp;yang memenuhi pertidaksamaan <span class=\"math-tex\">\\(\\frac{x^2-3x-4}{6x-4}&lt;0\\)<\/span>&nbsp;adalah&hellip;<\/p>","tags":"pertidaksamaan,sbmptn","subject":"Matematika","answers":[{"question_id":2,"id":6,"jawaban":"<p><span class=\"math-tex\">\\(-1&lt;x&lt;\\frac{2}{3}\\)<\/span>&nbsp;atau&nbsp;<span class=\"math-tex\">\\(x&gt;4\\)<\/span><\/p>","nilai":0},{"question_id":2,"id":7,"jawaban":"<p><span class=\"math-tex\">\\(x&lt;-1\\)<\/span>&nbsp;atau&nbsp;<span class=\"math-tex\">\\(\\frac{3}{2}&lt;x&lt;4\\)<\/span><\/p>","nilai":0},{"question_id":2,"id":8,"jawaban":"<p><span class=\"math-tex\">\\(-1&lt;x&lt;\\frac{2}{3}\\)<\/span>atau&nbsp;<span class=\"math-tex\">\\(x&gt;4\\)<\/span><\/p>","nilai":0},{"question_id":2,"id":9,"jawaban":"<p><span class=\"math-tex\">\\(x&lt;-1\\)<\/span>&nbsp;atau&nbsp;<span class=\"math-tex\">\\(\\frac{2}{3}&lt;x&lt;4\\)<\/span><\/p>","nilai":1},{"question_id":2,"id":10,"jawaban":"<p><span class=\"math-tex\">\\(x&gt;-1\\)<\/span>&nbsp;atau&nbsp;<span class=\"math-tex\">\\(x&lt;4\\)<\/span><\/p>","nilai":0}]}