{"id":20400,"question":"Semua pernyataan di bawah ini merupakan fungsi surat, kecuali\u2026","tags":"","subject":"Tes Wawasan Kebangsaan","answers":[{"question_id":20400,"id":101948,"jawaban":"Alat\/sarana komunikasi tertulis","nilai":0},{"question_id":20400,"id":101949,"jawaban":"Bukti tertulis yang mempunyai kekuatan hukum","nilai":0},{"question_id":20400,"id":101950,"jawaban":"Bukti historis","nilai":0},{"question_id":20400,"id":101951,"jawaban":"Duta masyarakat","nilai":1},{"question_id":20400,"id":101952,"jawaban":"a dan b benar","nilai":0}]}