{"id":20566,"question":"pmerintahan orde baru tidak berdaya menghadapi gejolak keunagnan eksternal yang bermuara pada krisis ekonomi terutama karena...","tags":"","subject":"Tes Wawasan Kebangsaan","answers":[{"question_id":20566,"id":102778,"jawaban":"banyak negara-negara donor berhenti memberikan  bantuan ekonomi","nilai":0},{"question_id":20566,"id":102779,"jawaban":"mengabaikan prinsip-prinsip ekonomi kerakyatan","nilai":1},{"question_id":20566,"id":102780,"jawaban":"terlambatnya hubungan kerja sama ekonomi dengan negara lain","nilai":0},{"question_id":20566,"id":102781,"jawaban":"stabilitas politik dan pemerintahan terganggu akibat gerakan sparatisme di berbagai daerah","nilai":0},{"question_id":20566,"id":102782,"jawaban":"pemerintah lebih memusatkan perhatian pada maslaah keamanan negara","nilai":0}]}