{"id":20806,"question":"pancasila sebagai paradigm dalam pembangunan sosial budaya adalah dengan mewujudkan...","tags":"","subject":"Tes Wawasan Kebangsaan","answers":[{"question_id":20806,"id":103978,"jawaban":"pembangunan sosial budaya dilaksanakan demi terwujudnya masyarakat yang demokratis, aman, tenteram, dan damai","nilai":1},{"question_id":20806,"id":103979,"jawaban":"pengembangan budaya daerah tertentu","nilai":0},{"question_id":20806,"id":103980,"jawaban":"pembangunan sosial dan budaya masyarakat indoneisa yang mengutamakan suku tertentu","nilai":0},{"question_id":20806,"id":103981,"jawaban":"menganggap nilai nilai yang ada di dalam masyarakat sudah tidak relavan lagi","nilai":0},{"question_id":20806,"id":103982,"jawaban":"menutup diri terhadap nilai nilai budaya luar","nilai":0}]}