{"id":20809,"question":"Pancasila sebagai landasan penyekenggaraan pemerintah dan kenegaraan merupakan funsi Pancasia sebagai...","tags":"","subject":"Tes Wawasan Kebangsaan","answers":[{"question_id":20809,"id":103993,"jawaban":"dasar negara","nilai":1},{"question_id":20809,"id":103994,"jawaban":"pandangan hidup bangsa","nilai":0},{"question_id":20809,"id":103995,"jawaban":"perjanjian luhur bangsa Indonesia","nilai":0},{"question_id":20809,"id":103996,"jawaban":"tujuan bangsa Indonesia","nilai":0},{"question_id":20809,"id":103997,"jawaban":"jiwa dan kepribadain bangsa indonesia","nilai":0}]}