{"id":2085,"question":"Pidato \u201c Indonesia Menggugat \u201d yang menghebohkan pemerintah Belanda di Indonesia dicetuskan oleh \u2026\u2026..","tags":"","subject":"Tes Wawasan Kebangsaan","answers":[{"question_id":2085,"id":10410,"jawaban":"Ir. Soekarno.","nilai":1},{"question_id":2085,"id":10411,"jawaban":"M. Hatta","nilai":0},{"question_id":2085,"id":10412,"jawaban":"H. Agus Salim","nilai":0},{"question_id":2085,"id":10413,"jawaban":"HOS. Cokroaminoto.","nilai":0},{"question_id":2085,"id":10414,"jawaban":"Sultan Syahril.","nilai":0}]}