{"id":21043,"question":"Masa penjajahan Jepang merupakan puncak penderitaan bangsa Indonesia. Namun penderitaan ini melahirkan nasionalisme dan rasa persaudaraan yang kuat, karena \u2026","tags":"","subject":"Tes Wawasan Kebangsaan","answers":[{"question_id":21043,"id":105159,"jawaban":"Penggunaan bahasa Indonesia sebagai bahasa resmi","nilai":1},{"question_id":21043,"id":105160,"jawaban":"Rakyat merasa senasib sepenanggungan","nilai":0},{"question_id":21043,"id":105161,"jawaban":"Dilarangnnya bahasa Belanda","nilai":0},{"question_id":21043,"id":105162,"jawaban":"Rakyat makn sadar akan ketidaktulusan Jepang sebagai saudara tua","nilai":0},{"question_id":21043,"id":105163,"jawaban":"Tergeraknya pergerakan nasional","nilai":0}]}