{"id":21077,"question":"Lambang yang ada pada burung Garuda mengandung  makna sesuai dengan sila yang ada pada pancasila. sila ke empat pada burung garuda dilambangkan dnegan...","tags":"","subject":"Tes Wawasan Kebangsaan","answers":[{"question_id":21077,"id":105328,"jawaban":"rantai","nilai":0},{"question_id":21077,"id":105329,"jawaban":"pohon beringin","nilai":0},{"question_id":21077,"id":105330,"jawaban":"kepala banteng","nilai":1},{"question_id":21077,"id":105331,"jawaban":"padi dan kapas","nilai":0},{"question_id":21077,"id":105332,"jawaban":"bintang","nilai":0}]}