{"id":21193,"question":"Kata sedap yang bermakna sinestesia terdapat dalam kalimat \u2026","tags":"","subject":"Tes Wawasan Kebangsaan","answers":[{"question_id":21193,"id":105908,"jawaban":"Makanan ini terasa sangat sedap.","nilai":0},{"question_id":21193,"id":105909,"jawaban":"Bunga sedam malam tumbuh di halaman rumahku.","nilai":0},{"question_id":21193,"id":105910,"jawaban":"Bumbu penyedap makanan itu mahal harganya","nilai":0},{"question_id":21193,"id":105911,"jawaban":"Kata-kata orang itu kurang sedap didengar.","nilai":1},{"question_id":21193,"id":105912,"jawaban":"Sayur buatan ibu sangat sedap.","nilai":0}]}