{"id":21214,"question":"Kalimat berikut, yang paling sopan, jika seseorang membantah pendapatnya dalam diskusi, adalah \u2026","tags":"","subject":"Tes Wawasan Kebangsaan","answers":[{"question_id":21214,"id":106013,"jawaban":"Saya sepenuhnya menolak pendapat Anda.","nilai":0},{"question_id":21214,"id":106014,"jawaban":"Saya tidak setuju dengan pendapat Anda karena pendapat tersebut tidak didukung oleh fakta dan alasan logis.","nilai":1},{"question_id":21214,"id":106015,"jawaban":"Anda harus memikirkan apa yang akan Anda katakan. Saya jelas tidak setuju dengan pendapat ini","nilai":0},{"question_id":21214,"id":106016,"jawaban":"Anda benar-benar tidak masuk akal.","nilai":0},{"question_id":21214,"id":106017,"jawaban":"Pendapat Anda sangat tidak mungkin untuk diterapkan.","nilai":0}]}