{"id":21304,"question":"hadirnya kehidupan masyarakat saat ini dipelopori oleh sejarah pergerakan nasional Indonesia yang dipelopori oleh...","tags":"","subject":"Tes Wawasan Kebangsaan","answers":[{"question_id":21304,"id":106463,"jawaban":"para kiai","nilai":0},{"question_id":21304,"id":106464,"jawaban":"kaum terpelajar","nilai":1},{"question_id":21304,"id":106465,"jawaban":"masyarakat pribumi","nilai":0},{"question_id":21304,"id":106466,"jawaban":"pedagang","nilai":0},{"question_id":21304,"id":106467,"jawaban":"kaum utama dan temanggung","nilai":0}]}