{"id":21646,"question":"Beberapa minggu yang lalu, Indonesia dihebohkan dengan berita yang dialami oleh salah seorang menteri dalam pemerintahan.\u00a0Menteri tersebut mengalami tragedi penusukan yang dilakukan oleh dua orang suami isteri ketika sedang melakukan kunjungan kerja di sebuah wilayah di Indonesia. Tindakan yang dilakukan oleh kedua orang tersebut tentu saja membuat heboh masyarakat dan menciptakan berbagai macam asumsi. Polisi mengatakan kedua orang tersebut telah terpapar paham radikalisme yang mengincar para pejabat negara yang mereka anggap salah. Tindakan yang dilakukan oleh para tersangka tersebut tidak mencerminkan perilaku yang menempatkan kepentingan bangsa dan malah melakukan tindakan radikal yang hanya mementingkan pribadi mereka atau hanya golongan mereka.  Tindakan tersebut merupakan penyimpangan\u00a0dari nilai-nilai Pancasila terutama dalam asas ...","tags":"","subject":"Tes Wawasan Kebangsaan","answers":[{"question_id":21646,"id":108173,"jawaban":"1","nilai":0},{"question_id":21646,"id":108174,"jawaban":"2","nilai":0},{"question_id":21646,"id":108175,"jawaban":"3","nilai":1},{"question_id":21646,"id":108176,"jawaban":"4","nilai":0},{"question_id":21646,"id":108177,"jawaban":"5","nilai":0}]}