{"id":21669,"question":"Bahasa Indonesia mempersatukan masyarakat Indonesia dan meningkatkan proses identifikasi penutur di seluruh Indonesia dari Sabang sampai Merauke.  Pernyataan di atas merupakan salah satu fungsi dari bahasa Indonesia yaitu sebagai\u2026","tags":"","subject":"Tes Wawasan Kebangsaan","answers":[{"question_id":21669,"id":108288,"jawaban":"Sebagai kerangka acuan","nilai":0},{"question_id":21669,"id":108289,"jawaban":"Sebagai pembawa kewibawaan","nilai":0},{"question_id":21669,"id":108290,"jawaban":"Sebagai ciri khas suatu bangsa","nilai":0},{"question_id":21669,"id":108291,"jawaban":"Sebagai alat pemersatu","nilai":1},{"question_id":21669,"id":108292,"jawaban":"Sebagai bahasa formal","nilai":0}]}