{"id":21976,"question":"Panitia kegiatan sosial menerima sumbangan beras beratnya 22\u00be kg dan 23\u00bc untuk dibagikan pada warga. Jika setiap warga menerima 2 kg, banyak warga yang menerima sumbangan beras tersebut adalah ...","tags":"","subject":"Tes Intelegensia Umum","answers":[{"question_id":21976,"id":109823,"jawaban":"15 Orang","nilai":0},{"question_id":21976,"id":109824,"jawaban":"18 Orang","nilai":0},{"question_id":21976,"id":109825,"jawaban":"20 Orang","nilai":0},{"question_id":21976,"id":109826,"jawaban":"21 Orang","nilai":0},{"question_id":21976,"id":109827,"jawaban":"23 Orang","nilai":1}]}