{"id":22015,"question":"12. Akar-akar persamaan kuadrat 3x2 + 2x - 5 = 0 adalah x1 dan x2. Hitunglah nilai dari 1\/x1 + 1\/x2.","tags":"","subject":"Tes Intelegensia Umum","answers":[{"question_id":22015,"id":110018,"jawaban":"1\/x1 + 1\/x2 = 0, 1","nilai":0},{"question_id":22015,"id":110019,"jawaban":"1\/x1 + 1\/x2 = 0, 2","nilai":0},{"question_id":22015,"id":110020,"jawaban":"1\/x1 + 1\/x2 = 0, 3","nilai":0},{"question_id":22015,"id":110021,"jawaban":"1\/x1 + 1\/x2 = 0, 4","nilai":1},{"question_id":22015,"id":110022,"jawaban":"1\/x1 + 1\/x2 = 0, 5","nilai":0}]}