{"id":22190,"question":"Sebuah kubus yang panjang rusuknya 10 cm dibelah-belah menjadi 8 kubus kecil yang sama besarnya. Berapakah panjang rusuk ke 8 kubus kecil tersebut?","tags":"","subject":"Tes Intelegensia Umum","answers":[{"question_id":22190,"id":110893,"jawaban":"2","nilai":0},{"question_id":22190,"id":110894,"jawaban":"3","nilai":0},{"question_id":22190,"id":110895,"jawaban":"4","nilai":0},{"question_id":22190,"id":110896,"jawaban":"5","nilai":1},{"question_id":22190,"id":110897,"jawaban":"6","nilai":0}]}