{"id":22284,"question":"Semua warga negara wajib ikut serta dalam upaya bela negara. Tindakan yang dapat mencerminkan bentuk   keikutsertaan siswa dalam upaya bela negara yaitu\u2026","tags":"","subject":"Tes Wawasan Kebangsaan","answers":[{"question_id":22284,"id":111363,"jawaban":"rajin belajar, mengikuti kegiatan PMR, dan upacara dengan khidmat","nilai":1},{"question_id":22284,"id":111364,"jawaban":"belajar PPKn, mengikuti kegiatan pramuka, dan ronda malam","nilai":0},{"question_id":22284,"id":111365,"jawaban":"ikut PMR, mengikuti kegiatan OSIS dan mengikuti karang taruna","nilai":0},{"question_id":22284,"id":111366,"jawaban":"siskamling, upacara bendera, dan piket kelas","nilai":0},{"question_id":22284,"id":111367,"jawaban":"bakti sosial, gotong royong di lingkungan rumah, dan rajin belajar","nilai":0}]}