{"id":22311,"question":"Salah satu pengamalan sila pancasila kedua adalah sebagai berikut:","tags":"","subject":"Tes Wawasan Kebangsaan","answers":[{"question_id":22311,"id":111498,"jawaban":"ikut ronda","nilai":0},{"question_id":22311,"id":111499,"jawaban":"berbicara santun","nilai":0},{"question_id":22311,"id":111500,"jawaban":"bertutur kata sopan kepada yg lbh tua","nilai":1},{"question_id":22311,"id":111501,"jawaban":"tidak membeda2kan perlakuan krn suku dan bahasa","nilai":0},{"question_id":22311,"id":111502,"jawaban":"tidak ada jawaban benar","nilai":0}]}