{"id":22329,"question":"Perbandingan permen Aurel, Rani san Dhea adalah 5 : 3 : 2. Sementara jumlah permen Aurel  dan Rani adalah 64. Jumlah permen tiga orang tersebut adalah.....","tags":"","subject":"Tes Intelegensia Umum","answers":[{"question_id":22329,"id":111588,"jawaban":"112","nilai":0},{"question_id":22329,"id":111589,"jawaban":"108","nilai":0},{"question_id":22329,"id":111590,"jawaban":"88","nilai":0},{"question_id":22329,"id":111591,"jawaban":"80","nilai":1},{"question_id":22329,"id":111592,"jawaban":"72","nilai":0}]}