{"id":22528,"question":"Penyelenggaraan EBTANAS pada tingkat SD, SLTP, dan SLTA memberi kontribusi positif kepada pembangunan sektor pendidikan terutama dalam ...","tags":"","subject":"Tes Wawasan Kebangsaan","answers":[{"question_id":22528,"id":112583,"jawaban":"Upaya pengendalian mutu pendidikan","nilai":1},{"question_id":22528,"id":112584,"jawaban":"Meningkatkan angka partisipasi pendidikan","nilai":0},{"question_id":22528,"id":112585,"jawaban":"Mengurangi biaya operasional pendidikan","nilai":0},{"question_id":22528,"id":112586,"jawaban":"Memeratakan tenaga dan sarana kependidikan","nilai":0},{"question_id":22528,"id":112587,"jawaban":"Meningkatkan nilai kelulusan setiap sekolah","nilai":0}]}