{"id":22773,"question":"Sistem pertahanan dan keamanan Indonesia mengalami perubahan substansial, yakni TNI sebagai kekuatan pertahanan Negara, sedangkan Polri menjadi kekuatan dengan fungsi sebagai ....","tags":"","subject":"Tes Wawasan Kebangsaan","answers":[{"question_id":22773,"id":113808,"jawaban":"Penyidikan dan keamanan publik","nilai":0},{"question_id":22773,"id":113809,"jawaban":"Keamanan dan ketertiban masyarakat","nilai":1},{"question_id":22773,"id":113810,"jawaban":"Pengendalian umum","nilai":0},{"question_id":22773,"id":113811,"jawaban":"Menjaga hukum dan peradilan","nilai":0},{"question_id":22773,"id":113812,"jawaban":"Sosial kemasyarakatan","nilai":0}]}