{"id":22909,"question":"Konferensi Tingkat Tinggi negara-negara berkembang yang dilaksanakan di Jakarta pada tanggal 30-31 Mei 2001 dengan nama kelompok ....","tags":"","subject":"Tes Wawasan Kebangsaan","answers":[{"question_id":22909,"id":114488,"jawaban":"G8","nilai":0},{"question_id":22909,"id":114489,"jawaban":"GN","nilai":0},{"question_id":22909,"id":114490,"jawaban":"G77","nilai":1},{"question_id":22909,"id":114491,"jawaban":"G15","nilai":0},{"question_id":22909,"id":114492,"jawaban":"G20","nilai":0}]}