{"id":23238,"question":"BPUPKI merupakan badan yang dibentuk oleh pemerintahan Jepang pada tanggal 29 April 1945. BPUPKI diketuai oleh ...","tags":"","subject":"Tes Wawasan Kebangsaan","answers":[{"question_id":23238,"id":116133,"jawaban":"Ir. Soekarno","nilai":0},{"question_id":23238,"id":116134,"jawaban":"Raden Pandji Soeroso","nilai":0},{"question_id":23238,"id":116135,"jawaban":"Moh. Yamin","nilai":0},{"question_id":23238,"id":116136,"jawaban":"K.H Wahid Hasyim","nilai":0},{"question_id":23238,"id":116137,"jawaban":"Dr. Radjiman Wedyodiningrat.","nilai":1}]}