{"id":23283,"question":"Mengembangkan sikap gotong royong dan kekeluargaan dalam lingkup masyarakat merupakan wujud sikap yang sesuai dengan sila \u2026","tags":"","subject":"Tes Wawasan Kebangsaan","answers":[{"question_id":23283,"id":116358,"jawaban":"Pertama","nilai":0},{"question_id":23283,"id":116359,"jawaban":"Kedua","nilai":0},{"question_id":23283,"id":116360,"jawaban":"Ketiga","nilai":0},{"question_id":23283,"id":116361,"jawaban":"Keempat","nilai":0},{"question_id":23283,"id":116362,"jawaban":"Kelima","nilai":1}]}