{"id":23351,"question":"Di bawah ini yang bukan merupakan hasil dari sidang PPKI tanggal 18 Agustus 1945 adalah ....","tags":"","subject":"Tes Wawasan Kebangsaan","answers":[{"question_id":23351,"id":116698,"jawaban":"Sila pertama diganti menjadi Ketuhanan Yang Maha Esa","nilai":0},{"question_id":23351,"id":116699,"jawaban":"Permusyawaratan Perwakilan diganti menjadi permusyawaran\/perwakilan","nilai":0},{"question_id":23351,"id":116700,"jawaban":"Mengesahkan dan menetapkan UUD","nilai":0},{"question_id":23351,"id":116701,"jawaban":"Menetapkan Ir. Soekarno dan Drs. Moh. Hatta menjadi presiden dan wakil presiden","nilai":0},{"question_id":23351,"id":116702,"jawaban":"Membentuk panitia perancang ekonomi dan keuangan","nilai":1}]}