{"id":23561,"question":"Bacalah kutipan teks berikut ini!  Setiap pagi hari Saddam membantu menyiapkan kue buatan ibunya untuk dibawa ke sekolah. Di sekolah, kue buatan ibunya itu akan dititipkan di kantin sekolah. Sepulang sekolah, Saddam akan membantu ibunya berjualan kue keliling kampungnya.  Penggambaran watak tokoh dalam cerpen tersebut dengan cara...","tags":"","subject":"Tes Wawasan Kebangsaan","answers":[{"question_id":23561,"id":117748,"jawaban":"Dialog antartokoh","nilai":0},{"question_id":23561,"id":117749,"jawaban":"Perilaku tokoh","nilai":1},{"question_id":23561,"id":117750,"jawaban":"Secara langsung","nilai":0},{"question_id":23561,"id":117751,"jawaban":"Pikiran tokoh","nilai":0},{"question_id":23561,"id":117752,"jawaban":"tidak ada jawaban benar","nilai":0}]}