{"id":23704,"question":"TEKNOLOGI INFORMASI dan KOMUNIKASI 1. Pada era pandemi covid 19, banyak berita hoax atau berita yang berlebihan yang dapat menyebabkan masyarkat menjadi lebih kawatir dan bisa berakibat buruk terhadap kesehatan fisik dan psikis. Ketika anda menerima broadcast whatsapp dari grup bagaimana anda menyikapinya ?","tags":"","subject":"Tes Karakteristik Pribadi","answers":[{"question_id":23704,"id":118463,"jawaban":"Memastikan kebenaran berita dengan membaca Koran dan berita ditelevisi untuk tidak menyebarkan jika berita itu salah","nilai":5},{"question_id":23704,"id":118464,"jawaban":"Menimbang nilai manfaat berita tersebut dan jika tidak bermanfaat hentikan berita dan tidak perlu disebarkan","nilai":4},{"question_id":23704,"id":118465,"jawaban":"Menyebarkan informasi yang saya terima, yang saya rasa beritanya benar","nilai":2},{"question_id":23704,"id":118466,"jawaban":"Menyebarkan informasiyang saya terima, yang saya rasa beritanya benar dan menghentikan menyebarkan jika ternyata beritanya salah","nilai":3},{"question_id":23704,"id":118467,"jawaban":"Menyebarkan kembali informasi yang diterima secara broadcast pada semua grup whatsap yang saya ikuti","nilai":1}]}