{"id":23742,"question":"Ketika rapat penting perusahaan, saat itu anda menjadi pemimpin rapat. Jika rapat itu gagal maka perusahaan akan mengalami kerugian besar, karena menyangkut kerjasama perusahaan dengan mitra, dan saat itu anda mendapatkan kabar (dari cs perusahaan), bahwa istri\/suami anda mengalami kecelakaan dan koma. Sikap anda....","tags":"","subject":"Tes Karakteristik Pribadi","answers":[{"question_id":23742,"id":118653,"jawaban":"Menghentikan rapat, karena kondisi suami \/ istri saya yang sedang dalam kondisi kritis","nilai":3},{"question_id":23742,"id":118654,"jawaban":"Meminta ijin kepada atasan saya dan menunjuk bawahan saya serta memberikan data lengkap untuk dapat melanjutkan rapat","nilai":5},{"question_id":23742,"id":118655,"jawaban":"Mengirim utusan ke rumah sakit untuk melihat kondisi pasien","nilai":2},{"question_id":23742,"id":118656,"jawaban":"Tetap melanjutkan rapat, dan segera ke rumah sakit setelah rapat selesai","nilai":1},{"question_id":23742,"id":118657,"jawaban":"Menunda rapat sampai besok","nilai":4}]}