{"id":23921,"question":"Pada akhir dari kerja normal, anda mempunyai suatu pekerjaan yag tak habis \u2013 habisnya dan harus selesai tepat waktu, apa yang akan anda lakukan ?","tags":"","subject":"Tes Karakteristik Pribadi","answers":[{"question_id":23921,"id":119548,"jawaban":"Pulang ke rumah dan menyelesaikan pekerjaan di hari berikutnya","nilai":1},{"question_id":23921,"id":119549,"jawaban":"Menyelesaikan pekerjaan tapi minta uang lembur","nilai":2},{"question_id":23921,"id":119550,"jawaban":"Menanyakan kepada pimpinan apakah ada uang lembur","nilai":3},{"question_id":23921,"id":119551,"jawaban":"Menyelesaikan pekerjaan dengan harapan memperoleh uang lembur","nilai":4},{"question_id":23921,"id":119552,"jawaban":"Menyelesaikan pekerjaan, tidak peduli ada uang lembur atau tidak","nilai":5}]}