{"id":23977,"question":"Sebuah semangka memiliki sisi terpanjang 18 cm. jika buah tersebut dibelah menjadi dua bagian yang sama besar, isi satu bagian semangka tersebut adalah...","tags":"","subject":"Tes Intelegensia Umum","answers":[{"question_id":23977,"id":119826,"jawaban":"6104,16 cm\u00b3","nilai":0},{"question_id":23977,"id":119827,"jawaban":"4526,12 cm\u00b3","nilai":0},{"question_id":23977,"id":119828,"jawaban":"3052,08 cm\u00b3","nilai":0},{"question_id":23977,"id":119829,"jawaban":"2104,18 cm\u00b3","nilai":0},{"question_id":23977,"id":119830,"jawaban":"1526,04 cm\u00b3","nilai":1}]}