{"id":2444,"question":"Dalam rangka pengembanagan ekonomi daerah di dalam wadah NKRI, daerah yang mendapatkan perhatian khusus pada amanat GBHN adalah ....","tags":"","subject":"Tes Wawasan Kebangsaan","answers":[{"question_id":2444,"id":12205,"jawaban":"Daerah lstimewa Aceh","nilai":1},{"question_id":2444,"id":12206,"jawaban":"Daerah lstimewa Yogyakarta","nilai":0},{"question_id":2444,"id":12207,"jawaban":"Daerah Khusus lbukota","nilai":0},{"question_id":2444,"id":12208,"jawaban":"Daerah Kepulauan Seribu","nilai":0},{"question_id":2444,"id":12209,"jawaban":"Daerah Kalimantan","nilai":0}]}