{"id":2492,"question":"Untuk membina kehidupan masyarakat, salah satu kewajiban setiap warga negara Indonesia adalah ....","tags":"","subject":"Tes Wawasan Kebangsaan","answers":[{"question_id":2492,"id":12445,"jawaban":"Menaati aturan dalam kehidupan bermasyarakat dan bernegara","nilai":1},{"question_id":2492,"id":12446,"jawaban":"Menunaikan kewajiban membayar pajak pada waktunya","nilai":0},{"question_id":2492,"id":12447,"jawaban":"Selalu aktif dalam menjaga keamanan lingkungan pada malam hari","nilai":0},{"question_id":2492,"id":12448,"jawaban":"Menaati panggilan negara melaksanakan wajib militer","nilai":0},{"question_id":2492,"id":12449,"jawaban":"Bergotong royong membantu kegiatan membangun pos kamling","nilai":0}]}