{"id":2706,"question":"Pengakuan hak asasi sosial yang berupa keadilan dan pengakuan hak asasi ekonomi yang berupa kemakmuran dan kesejahteraan merupakan makna yang terkandung pada alinea pembukaan UUD 1945 ...","tags":"","subject":"Tes Wawasan Kebangsaan","answers":[{"question_id":2706,"id":13515,"jawaban":"I","nilai":0},{"question_id":2706,"id":13516,"jawaban":"II","nilai":1},{"question_id":2706,"id":13517,"jawaban":"III","nilai":0},{"question_id":2706,"id":13518,"jawaban":"IV","nilai":0},{"question_id":2706,"id":13519,"jawaban":"I dan II","nilai":0}]}