{"id":3088,"question":"Dalam makna Pembukaan UUD 1945 terutama dalam alenia pertama, bagi bangsa Indonesia antara lain mengandung maksud sebagai ....","tags":"","subject":"Tes Wawasan Kebangsaan","answers":[{"question_id":3088,"id":15425,"jawaban":"Sumber dari segala hukum yang berlaku atau tertib hukum","nilai":0},{"question_id":3088,"id":15426,"jawaban":"Peraturan perundang-undangan yang tertinggi","nilai":0},{"question_id":3088,"id":15427,"jawaban":"Deklarasi terbentuknya suatu bangsa dan negara Indonesia","nilai":0},{"question_id":3088,"id":15428,"jawaban":"Pernyataan kemerdekaan yang terperinci","nilai":0},{"question_id":3088,"id":15429,"jawaban":"Pernyataan tentang hak-hak asasi manusia yang paling mendasar","nilai":1}]}