{"id":3325,"question":"Pada dasarnya nilai-nilai pancasila diambil dari \u2026","tags":"","subject":"Tes Wawasan Kebangsaan","answers":[{"question_id":3325,"id":16610,"jawaban":"Budaya penjajah","nilai":0},{"question_id":3325,"id":16611,"jawaban":"Budaya negara-negara maju","nilai":0},{"question_id":3325,"id":16612,"jawaban":"Budaya asing yang terkenal","nilai":0},{"question_id":3325,"id":16613,"jawaban":"Budaya dari paham-paham besar didunia","nilai":0},{"question_id":3325,"id":16614,"jawaban":"Budaya sendiri yang telah mengakar dalam jiwa bangsa","nilai":1}]}