{"id":3670,"question":"Dalam beberapa hari ini dunia Maya kembali dihebohkan dengan video penggerebekan sepasang muda mudi yang diduga tengah berbuat mesum di Cikupa , Tangerang ,Banten pada tanggal 20 November 2018. Namun, setelah dilakukan penyelidikan, ternyata pasangan muda mudi tersebut menjadi korban salah tuduh . Video yang viral tersebut memperlihatkan bagaimana para warga mengarak mereka keliling kampung dengan kondisi setengah telanjang. Hal semacam ini telah melanggar salah satu sila dalam Pancasila yaitu sila ke ?","tags":"","subject":"Tes Wawasan Kebangsaan","answers":[{"question_id":3670,"id":18335,"jawaban":"1","nilai":0},{"question_id":3670,"id":18336,"jawaban":"2","nilai":1},{"question_id":3670,"id":18337,"jawaban":"3","nilai":0},{"question_id":3670,"id":18338,"jawaban":"4","nilai":0},{"question_id":3670,"id":18339,"jawaban":"5","nilai":0}]}