{"id":3785,"question":"Anda menemukan sebuah artikel di internet yang ternyata dapat membantu pekerjaan anda. Anda \u2026.","tags":"","subject":"Tes Karakteristik Pribadi","answers":[{"question_id":3785,"id":18910,"jawaban":"Memberitahu rekan kerja atau teman dekat anda","nilai":1},{"question_id":3785,"id":18911,"jawaban":"Menerapkan dalam pekerjaan","nilai":4},{"question_id":3785,"id":18912,"jawaban":"Memberitahu saat rapat ke semua rekan kerja","nilai":5},{"question_id":3785,"id":18913,"jawaban":"Memberitahu ke rekan yang ingin mengetahuinya","nilai":2},{"question_id":3785,"id":18914,"jawaban":"Memberitahu ke teman anda dan menerapkanya","nilai":3}]}