{"id":593,"question":"presiden menerima penempatan duta negara lain dengan memperhatikan pertimbangan dewan perwakilan rakyat adalah bunyi pasal.... UUD NRI tahun 1945","tags":"","subject":"Tes Wawasan Kebangsaan","answers":[{"question_id":593,"id":2955,"jawaban":"pasal 12","nilai":0},{"question_id":593,"id":2956,"jawaban":"pasal 13","nilai":1},{"question_id":593,"id":2957,"jawaban":"pasal 14","nilai":0},{"question_id":593,"id":2958,"jawaban":"pasal 15","nilai":0},{"question_id":593,"id":2959,"jawaban":"pasal 16","nilai":0}]}