{"id":711,"question":"penulisan unsur serapan yang benar terdapat pada kalimat","tags":"","subject":"Tes Wawasan Kebangsaan","answers":[{"question_id":711,"id":3545,"jawaban":"aerodinamika pesawat harus diperhitungkan secara matang","nilai":1},{"question_id":711,"id":3546,"jawaban":"rimunerasi mulai berlaku serentak di seluruh lembaga pemerintahan","nilai":0},{"question_id":711,"id":3547,"jawaban":"negara maju berbasis pada sistim pemerintahan yang transparan","nilai":0},{"question_id":711,"id":3548,"jawaban":"dalam dasawarsa terakhir banyak tumbuh apotik 24 jam","nilai":0},{"question_id":711,"id":3549,"jawaban":"pembangunan apartemen harus berbasis pada analisa kebutuhan","nilai":0}]}