{"id":752,"question":"Pendiri organisasi Taman Siswa adalah R.M. Soewani Soeryaningrat atau yang sering kita sebut dengan Ki Hajar Dewantoro. Dia adalah tokoh bangsawan yang pada waktu itu menjadi pencetus organisasi pendidikan pertama di Indonesia.  Ki Hajar Dewantara yang dulunya pernah menjadi wartawan dan aktif di dunia politik dikenal sebagai sosok bangsawan yang memiliki pemikiran jauh ke depan. Dia aktif sebagai penulis yang memiliki kebudayaan tinggi dan sangat termotivasi untuk berskolah di Belanda.  Pada tahun 1919 setelah pulang dari Belanda, Ki Hajar Dewantara bersama dengan teman-temannya mengadakan pertemuan di halaman rumahnya. Halaman rumah itu kini menjadi pendopo Taman Siswa  yang berlokasi di kota","tags":"","subject":"Tes Wawasan Kebangsaan","answers":[{"question_id":752,"id":3750,"jawaban":"Yogyakarta","nilai":1},{"question_id":752,"id":3751,"jawaban":"Semarang","nilai":0},{"question_id":752,"id":3752,"jawaban":"Surabaya","nilai":0},{"question_id":752,"id":3753,"jawaban":"Bali","nilai":0},{"question_id":752,"id":3754,"jawaban":"Bandung","nilai":0}]}