{"id":92,"question":"<p><strong>Analogi<\/strong><\/p>\r\n\r\n<p>PETANI : CANGKUL =<\/p>","tags":"sbmptn,stan,cpns,tiu,tpa,analogi","subject":"Tes Intelegensia Umum","answers":[{"question_id":92,"id":451,"jawaban":"<p>Raja : mahkota<\/p>","nilai":0},{"question_id":92,"id":452,"jawaban":"<p>Nelayan : jaring<\/p>","nilai":1},{"question_id":92,"id":453,"jawaban":"<p>Dalang : cerita<\/p>","nilai":0},{"question_id":92,"id":454,"jawaban":"<p>Penjahit : baju<\/p>","nilai":0},{"question_id":92,"id":455,"jawaban":"<p>Wartawan : berita<\/p>","nilai":0}]}