{"id":969,"question":"NU dan muhammadiyah organisasi merasa yang tidak asing lagi bagi masyarakat indonesia. keanggotaan Nu secara umum berbasis masyarakat pedesaan, sedangkan muhammadyah berbasis masyarakat perkotaan. pada masa pergerakan nasional kedua organisasi ini memiliki persamaan dalam aktifitas pergerakan yaitu...","tags":"","subject":"Tes Wawasan Kebangsaan","answers":[{"question_id":969,"id":4833,"jawaban":"corak pergerakan bersifat sosial politik","nilai":0},{"question_id":969,"id":4834,"jawaban":"untuk mendukung pemerintah kolonial","nilai":0},{"question_id":969,"id":4835,"jawaban":"bergerak di bidang politik dan keagamaan","nilai":0},{"question_id":969,"id":4836,"jawaban":"bergerak di bidang sosial keagamaan","nilai":1},{"question_id":969,"id":4837,"jawaban":"berani menentang kebijakan pemerintah","nilai":0}]}