{"id":986,"question":"Negosiasi adalah \u2026.","tags":"","subject":"Tes Wawasan Kebangsaan","answers":[{"question_id":986,"id":4917,"jawaban":"wujud interaksi sosial yang bertujuan untuk mencari kesepakatan bersama dari kedua belah pihak","nilai":1},{"question_id":986,"id":4918,"jawaban":"perdebatan antara pihak satu dengan pihak lain","nilai":0},{"question_id":986,"id":4919,"jawaban":"penggambaran suatu masalah sesuai dengan kejadian yang terjadi","nilai":0},{"question_id":986,"id":4920,"jawaban":"kesimpulan teks deskriptif","nilai":0},{"question_id":986,"id":4921,"jawaban":"tidak ada jawaban benar","nilai":0}]}